LICENSE.txt
README.txt
py2rpm.ini
requirements-3rdparty.txt
requirements-doc.txt
requirements-hoplite.txt
tox.ini
docs/_sources/configuration.file.rst.txt
docs/_sources/configuration.rst.txt
docs/_sources/index.rst.txt
docs/_sources/libnrdpd.config.rst.txt
docs/_sources/libnrdpd.error.rst.txt
docs/_sources/libnrdpd.main.rst.txt
docs/_sources/libnrdpd.nrdp.rst.txt
docs/_sources/libnrdpd.rst.txt
docs/_sources/libnrdpd.schedule.rst.txt
docs/_sources/libnrdpd.task.rst.txt
docs/_sources/libnrdpd.util.rst.txt
docs/_sources/nrdpd.rst.txt
libnrdpd/__about__.py
libnrdpd/__init__.py
libnrdpd/config.py
libnrdpd/error.py
libnrdpd/main.py
libnrdpd/nrdp.py
libnrdpd/schedule.py
libnrdpd/task.py
libnrdpd/util.py
tests/config/config-bad-url.ini
tests/config/config-mvp.ini
tests/config/config-valid.ini
tests/config/conf.d/000-defaults.ini
tests/config/conf.d/001-test.ini
tests/config/conf.d/003-config-token.ini
tests/config/conf.d/004-config.ini
nrdp_daemon-1.0.27.dist-info/METADATA
nrdp_daemon-1.0.27.dist-info/WHEEL
nrdp_daemon-1.0.27.dist-info/entry_points.txt
nrdp_daemon-1.0.27.dist-info/licenses/LICENSE.txt
nrdp_daemon-1.0.27.dist-info/RECORD
